{
  "users": {
    "marca": [
      {
        "nome": "Chevrolet",
        "modelos": [
          {
            "nome": "onix",
            "placa": "JKL3T12",
            "cor": "branco"
          },
          {
            "nome": "prisma",
            "placa": "PQR6A78",
            "cor": "azul"
          },
          {
            "nome": "spin",
            "placa": "MNO5Y34",
            "cor": "preto"
          }
        ]
      },
      {
        "nome": "Ford",
        "modelos": [
          {
            "nome": "ka",
            "placa": "ABC1D23",
            "cor": "cinza"
          },
          {
            "nome": "fiesta",
            "placa": "XYZ4E56",
            "cor": "Preto"
          },
          {
            "nome": "ecoSport",
            "placa": "QWE7R89",
            "cor": "cinza"
          }
        ]
      }
    ],
    "motorista": [
      {
        "nome": "gleidson",
        "cnh": "12345678900",
        "estado": "livre"
      },
      {
        "nome": "Edivan",
        "cnh": "98765432101",
        "estado": "livre"
      },
      {
        "nome": "Yara",
        "cnh": "45678912302",
        "estado": "livre"
      },
      {
        "nome": "Luis",
        "cnh": "78912345603",
        "estado": "livre"
      },
      {
        "nome": "Pamplona",
        "cnh": "65432198704",
        "estado": "livre"
      },
      {
        "nome": "Deda",
        "cnh": "32198765405",
        "estado": "livre"
      }
    ]
  }
}